odoo/addons/rma_sale_mrp/README.rst
odoo/addons/rma_sale_mrp/__init__.py
odoo/addons/rma_sale_mrp/__manifest__.py
odoo/addons/rma_sale_mrp/i18n/es.po
odoo/addons/rma_sale_mrp/i18n/it.po
odoo/addons/rma_sale_mrp/i18n/pt.po
odoo/addons/rma_sale_mrp/i18n/pt_BR.po
odoo/addons/rma_sale_mrp/i18n/rma_sale_mrp.pot
odoo/addons/rma_sale_mrp/models/__init__.py
odoo/addons/rma_sale_mrp/models/account_move.py
odoo/addons/rma_sale_mrp/models/rma.py
odoo/addons/rma_sale_mrp/models/sale_order.py
odoo/addons/rma_sale_mrp/readme/CONTRIBUTORS.rst
odoo/addons/rma_sale_mrp/readme/DESCRIPTION.rst
odoo/addons/rma_sale_mrp/readme/ROADMAP.rst
odoo/addons/rma_sale_mrp/readme/USAGE.rst
odoo/addons/rma_sale_mrp/security/ir.model.access.csv
odoo/addons/rma_sale_mrp/static/description/icon.png
odoo/addons/rma_sale_mrp/static/description/index.html
odoo/addons/rma_sale_mrp/tests/__init__.py
odoo/addons/rma_sale_mrp/tests/test_rma_sale_mrp.py
odoo/addons/rma_sale_mrp/views/report_rma.xml
odoo/addons/rma_sale_mrp/views/rma_views.xml
odoo/addons/rma_sale_mrp/views/sale_order_portal_template.xml
odoo/addons/rma_sale_mrp/wizard/__init__.py
odoo/addons/rma_sale_mrp/wizard/sale_order_rma_wizard.py
odoo/addons/rma_sale_mrp/wizard/sale_order_rma_wizard_views.xml
odoo_addon_rma_sale_mrp-16.0.2.2.1.dist-info/METADATA
odoo_addon_rma_sale_mrp-16.0.2.2.1.dist-info/WHEEL
odoo_addon_rma_sale_mrp-16.0.2.2.1.dist-info/top_level.txt
odoo_addon_rma_sale_mrp-16.0.2.2.1.dist-info/RECORD
