Metadata-Version: 2.1
Name: odoo-addon-rma_sale_mrp
Version: 16.0.2.2.1
Summary: Allow doing RMAs from MRP kits
Home-page: https://github.com/OCA/rma
Author: Tecnativa, Odoo Community Association (OCA)
Author-email: support@odoo-community.org
License: AGPL-3
Classifier: Programming Language :: Python
Classifier: Framework :: Odoo
Classifier: Framework :: Odoo :: 16.0
Classifier: License :: OSI Approved :: GNU Affero General Public License v3
Classifier: Development Status :: 4 - Beta
Requires-Python: >=3.10
Requires-Dist: odoo-addon-rma-sale<16.1dev,>=16.0dev
Requires-Dist: odoo<16.1dev,>=16.0a
